{
 "total_rating": "4.7",
 "welfare_benefits": "4.7",
 "work_life_balance": "4.0",
 "company_culture": "4.3",
 "Promotion_opportunity": "4.7",
 "oner": "5.0",
 "review": [
  {
   "title": "폭발적인 성장을 지원 해 주는 곳, 폭발적인 성장이 가능한 곳",
   "pros": "장점내 성장이 회사의 성장이라는 점을 확실하게 인지하고 경험시켜 주는 점",
   "cons": "단점본인이 수직적이고 자율속의 책임감을 좋아하지 않는 사람이라면 힘들수도 있음",
   "wish_to_oner": "경영진에 바라는 점좋은 욕심이 많은 팀원들이 더 동기부여가 될 수 있는 시스템을 구축 해 줬으면 함",
   "outlook_for_next_year": "1년 후 성장하고 있을 것 같아요",
   "recommand": "기업을 추천해요"
  },
  {
   "title": "자기 업무를 주도적으로 할 수 있는 기업",
   "pros": "장점자기가 일 한만큼 성장함. 주도적인 업무 진행 가능함. 의사결정 과정이 신속함.\r\n스케줄을 짜는데 자유도가 높고, 업무 성과에 대한 압박이 적음.",
   "cons": "단점체계적인 시스템은 아직 부족함. 만들어 나가는 과정에서 혼란이 있을 수 있음.\r\n회사를 만든지 얼마 되지 않아 업무 분장이 명확하지 않은 부분이 있음.\r\n다양한 업무를 처리 할 수 있어야 함.",
   "wish_to_oner": "경영진에 바라는 점초심을 잃지 말고 끝까지 유지해주길.",
   "outlook_for_next_year": "1년 후 성장하고 있을 것 같아요",
   "recommand": "기업을 추천해요"
  },
  {
   "title": "체계가 잡혀있고 장기 근속이 가능한 안정적인 회사",
   "pros": "장점연차 자유롭게 사용 가능,가족 같은 분위기,회식 강요 없음,월급 안 밀림,지하철 역 3분 거리 편리한 출퇴근,자유로운 복장,명절 상품권 지급,도서 무제한 구입 지원,청년 내일 채움 공제 가입",
   "cons": "단점스타트업이라 아직 직원이 많지 않다 보니 더 좋고 능력 있으신 분들과 같이 즐겁게 일하고 싶어요!!\r\n굳이 단점을 말하자면,작은 회사다 보니까 일이 많고, 직접적으로 제 직무가 아닌 업무도 해야 할 때도 있어요",
   "wish_to_oner": "경영진에 바라는 점지금처럼 앞으로도 쭉~~~ 직원들 의견을 긍정적으로 반영해주시는 멋있는 대표님이 되어주세요^^ 회사가 빠르게 성장해서 특별 성과급 연차 외 포상 휴가도 기대해보고 싶습니다!!!!",
   "outlook_for_next_year": "1년 후 성장하고 있을 것 같아요",
   "recommand": "기업을 추천해요"
  },
  {
   "title": "기업에 대한 성장가능성은 있으나 장기근무는 어려움",
   "pros": "장점식대 제공되고 수습기간에도 연차 사용가능 , 급여 잘 나옴",
   "cons": "단점직원에 대한 관심 제로, 연장근무 존재, 내부 분위기 좋지 않음",
   "wish_to_oner": "경영진에 바라는 점현장 분위기에 대한 관심이 필요하고 개선을 위한 노력을 본사에서 해야 한다고 봅니다",
   "outlook_for_next_year": "1년 후 하락하고 있을 것 같아요",
   "recommand": "기업을 추천하지 않아요"
  }
 ]
}